{
  "meta": {
    "date": "20260423",
    "dateDisplay": "4月（截至23日）",
    "fetchedAt": "2026-04-24T06:29:46.730Z",
    "source": "Naver Finance / Multi-source v3",
    "updateCount": 6
  },
  "shiftUp": {
    "code": "462870",
    "name": "Shift Up",
    "nameKr": "시프트업",
    "color": "#ff6b9d",
    "price": "34,750",
    "previousClose": "34,550",
    "high": "35,150",
    "low": "34,300",
    "change": "200",
    "changePercent": "+0.58%",
    "changeClass": "up",
    "per": "10.67",
    "pbr": "2.22",
    "marketCap": "2.04兆元"
  },
  "companies": [
    {
      "code": "036570",
      "name": "NC",
      "nameKr": "엔씨",
      "color": "#3b82f6",
      "price": "271,000",
      "change": "-1.45%",
      "changeClass": "down",
      "per": "16.91"
    },
    {
      "code": "259960",
      "name": "Krafton",
      "nameKr": "크래프톤",
      "color": "#f59e0b",
      "price": "266,500",
      "change": "+0.38%",
      "changeClass": "up",
      "per": "17.94"
    },
    {
      "code": "251270",
      "name": "Netmarble",
      "nameKr": "넷마블",
      "color": "#ef4444",
      "price": "49,650",
      "change": "-2.84%",
      "changeClass": "down",
      "per": "19.25"
    },
    {
      "code": "225570",
      "name": "Nexon Games",
      "nameKr": "넥슨게임즈",
      "color": "#22c55e",
      "price": "12,020",
      "change": "-0.74%",
      "changeClass": "down",
      "per": "N/A"
    },
    {
      "code": "263750",
      "name": "Pearl Abyss",
      "nameKr": "펄어비스",
      "color": "#ec4899",
      "price": "55,600",
      "change": "-3.64%",
      "changeClass": "down",
      "per": "N/A"
    }
  ],
  "perComparison": [
    {
      "code": "462870",
      "name": "Shift Up",
      "color": "#ff6b9d",
      "price": "34,750",
      "per": 10.67,
      "perRaw": "10.67"
    },
    {
      "code": "036570",
      "name": "NC",
      "color": "#3b82f6",
      "price": "271,000",
      "per": 16.91,
      "perRaw": "16.91"
    },
    {
      "code": "259960",
      "name": "Krafton",
      "color": "#f59e0b",
      "price": "266,500",
      "per": 17.94,
      "perRaw": "17.94"
    },
    {
      "code": "251270",
      "name": "Netmarble",
      "color": "#ef4444",
      "price": "49,650",
      "per": 19.25,
      "perRaw": "19.25"
    }
  ],
  "chartData": [
    {
      "date": "20260406",
      "label": "4/6",
      "price": 32900
    },
    {
      "date": "20260407",
      "label": "4/7",
      "price": 32000
    },
    {
      "date": "20260408",
      "label": "4/8",
      "price": 33400
    },
    {
      "date": "20260409",
      "label": "4/9",
      "price": 33200
    },
    {
      "date": "20260410",
      "label": "4/10",
      "price": 32850
    },
    {
      "date": "20260413",
      "label": "4/13",
      "price": 32850
    },
    {
      "date": "20260414",
      "label": "4/14",
      "price": 33750
    },
    {
      "date": "20260415",
      "label": "4/15",
      "price": 33000
    },
    {
      "date": "20260416",
      "label": "4/16",
      "price": 33700
    },
    {
      "date": "20260417",
      "label": "4/17",
      "price": 33500
    },
    {
      "date": "20260420",
      "label": "4/20",
      "price": 33750
    },
    {
      "date": "20260421",
      "label": "4/21",
      "price": 34100
    },
    {
      "date": "20260422",
      "label": "4/22",
      "price": 34550
    },
    {
      "date": "20260423",
      "label": "4/23",
      "price": 34750
    }
  ]
}