{
  "meta": {
    "date": "20260415",
    "dateDisplay": "4月（截至15日）",
    "fetchedAt": "2026-04-16T08:43:41.991Z",
    "source": "Naver Finance / Multi-source v3",
    "updateCount": 6
  },
  "shiftUp": {
    "code": "462870",
    "name": "Shift Up",
    "nameKr": "시프트업",
    "color": "#ff6b9d",
    "price": "33,000",
    "previousClose": "33,750",
    "high": "34,050",
    "low": "33,000",
    "change": "-750",
    "changePercent": "-2.22%",
    "changeClass": "down",
    "per": "10.33",
    "pbr": "2.15",
    "marketCap": "1.95兆元"
  },
  "companies": [
    {
      "code": "259960",
      "name": "Krafton",
      "nameKr": "크래프톤",
      "color": "#f59e0b",
      "price": "244,000",
      "change": "+2.09%",
      "changeClass": "up",
      "per": "16.61"
    },
    {
      "code": "036570",
      "name": "NC",
      "nameKr": "엔씨",
      "color": "#3b82f6",
      "price": "247,500",
      "change": "-0.40%",
      "changeClass": "down",
      "per": "16.63"
    },
    {
      "code": "251270",
      "name": "Netmarble",
      "nameKr": "넷마블",
      "color": "#ef4444",
      "price": "50,800",
      "change": "+0.20%",
      "changeClass": "up",
      "per": "19.82"
    },
    {
      "code": "225570",
      "name": "Nexon Games",
      "nameKr": "넥슨게임즈",
      "color": "#22c55e",
      "price": "11,850",
      "change": "-0.34%",
      "changeClass": "down",
      "per": "N/A"
    },
    {
      "code": "263750",
      "name": "Pearl Abyss",
      "nameKr": "펄어비스",
      "color": "#ec4899",
      "price": "56,000",
      "change": "-3.28%",
      "changeClass": "down",
      "per": "N/A"
    }
  ],
  "perComparison": [
    {
      "code": "462870",
      "name": "Shift Up",
      "color": "#ff6b9d",
      "price": "33,000",
      "per": 10.33,
      "perRaw": "10.33"
    },
    {
      "code": "259960",
      "name": "Krafton",
      "color": "#f59e0b",
      "price": "244,000",
      "per": 16.61,
      "perRaw": "16.61"
    },
    {
      "code": "036570",
      "name": "NC",
      "color": "#3b82f6",
      "price": "247,500",
      "per": 16.63,
      "perRaw": "16.63"
    },
    {
      "code": "251270",
      "name": "Netmarble",
      "color": "#ef4444",
      "price": "50,800",
      "per": 19.82,
      "perRaw": "19.82"
    }
  ],
  "chartData": [
    {
      "date": "20260401",
      "label": "4/1",
      "price": 33900
    },
    {
      "date": "20260402",
      "label": "4/2",
      "price": 32250
    },
    {
      "date": "20260403",
      "label": "4/3",
      "price": 33000
    },
    {
      "date": "20260406",
      "label": "4/6",
      "price": 32900
    },
    {
      "date": "20260407",
      "label": "4/7",
      "price": 32000
    },
    {
      "date": "20260408",
      "label": "4/8",
      "price": 33400
    },
    {
      "date": "20260409",
      "label": "4/9",
      "price": 33200
    },
    {
      "date": "20260410",
      "label": "4/10",
      "price": 32850
    },
    {
      "date": "20260413",
      "label": "4/13",
      "price": 32850
    },
    {
      "date": "20260414",
      "label": "4/14",
      "price": 33750
    },
    {
      "date": "20260415",
      "label": "4/15",
      "price": 33000
    }
  ]
}